odoo10_addon_hr_holidays_hour-10.0.1.0.0.99.dev6-py2.7-nspkg.pth
odoo/addons/hr_holidays_hour/README.rst
odoo/addons/hr_holidays_hour/__init__.py
odoo/addons/hr_holidays_hour/__manifest__.py
odoo/addons/hr_holidays_hour/i18n/de.po
odoo/addons/hr_holidays_hour/i18n/hr_holidays_hour.pot
odoo/addons/hr_holidays_hour/models/__init__.py
odoo/addons/hr_holidays_hour/models/hr_employee.py
odoo/addons/hr_holidays_hour/models/hr_holidays.py
odoo/addons/hr_holidays_hour/models/hr_holidays_status.py
odoo/addons/hr_holidays_hour/models/resource_calendar.py
odoo/addons/hr_holidays_hour/report/__init__.py
odoo/addons/hr_holidays_hour/report/hr_holidays_report.py
odoo/addons/hr_holidays_hour/report/hr_holidays_report_view.xml
odoo/addons/hr_holidays_hour/security/ir.model.access.csv
odoo/addons/hr_holidays_hour/static/description/icon.png
odoo/addons/hr_holidays_hour/tests/__init__.py
odoo/addons/hr_holidays_hour/tests/test_leave_hours.py
odoo/addons/hr_holidays_hour/tests/test_resource.py
odoo/addons/hr_holidays_hour/views/hr_holidays.xml
odoo/addons/hr_holidays_hour/views/hr_holidays_status.xml
odoo10_addon_hr_holidays_hour-10.0.1.0.0.99.dev6.dist-info/METADATA
odoo10_addon_hr_holidays_hour-10.0.1.0.0.99.dev6.dist-info/RECORD
odoo10_addon_hr_holidays_hour-10.0.1.0.0.99.dev6.dist-info/WHEEL
odoo10_addon_hr_holidays_hour-10.0.1.0.0.99.dev6.dist-info/namespace_packages.txt
odoo10_addon_hr_holidays_hour-10.0.1.0.0.99.dev6.dist-info/top_level.txt
